tf2backpackpy
