Metadata-Version: 1.0
Name: tf2backpackpy
Version: 1.1.1
Summary: A library for using the backpack.tf API
Home-page: https://github.com/Zwork101/backpack.py
Author: Zwork101
Author-email: zwork101@gmail.com
License: MIT
Platform: UNKNOWN
